[{"flatpakAppId":"org.rncbc.drumkv1","name":"drumkv1","summary":"an old-school drumk-kit sampler","currentReleaseVersion":"1.0.0","currentReleaseDate":"2022-01-01","iconDesktopUrl":"http://localhost:7777/repo/appstream/x86_64/icons/128x128/org.rncbc.drumkv1","iconMobileUrl":"http://localhost:7777/repo/appstream/x86_64/icons/128x128/org.rncbc.drumkv1","inStoreSinceDate":null},{"flatpakAppId":"net.sourceforge.kmetronome","name":"Drumstick Metronome","summary":"Drumstick MIDI Metronome based on the ALSA Sequencer","currentReleaseVersion":"1.0.0","currentReleaseDate":"2022-01-01","iconDesktopUrl":"http://localhost:7777/repo/appstream/x86_64/icons/128x128/net.sourceforge.kmetronome","iconMobileUrl":"http://localhost:7777/repo/appstream/x86_64/icons/128x128/net.sourceforge.kmetronome","inStoreSinceDate":null},{"flatpakAppId":"net.sourceforge.drumstick-drumgrid","name":"drumstick-drumgrid","summary":"Simple MIDI rhythm box based on ALSA Sequencer","currentReleaseVersion":"1.0.0","currentReleaseDate":"2022-01-01","iconDesktopUrl":"http://localhost:7777/repo/appstream/x86_64/icons/128x128/net.sourceforge.drumstick-drumgrid","iconMobileUrl":"http://localhost:7777/repo/appstream/x86_64/icons/128x128/net.sourceforge.drumstick-drumgrid","inStoreSinceDate":null},{"flatpakAppId":"net.sourceforge.drumstick-guiplayer","name":"drumstick-guiplayer","summary":"Simple MIDI file player based on ALSA Sequencer","currentReleaseVersion":"1.0.0","currentReleaseDate":"2022-01-01","iconDesktopUrl":"http://localhost:7777/repo/appstream/x86_64/icons/128x128/net.sourceforge.drumstick-guiplayer","iconMobileUrl":"http://localhost:7777/repo/appstream/x86_64/icons/128x128/net.sourceforge.drumstick-guiplayer","inStoreSinceDate":null},{"flatpakAppId":"net.sourceforge.drumstick-vpiano","name":"drumstick-vpiano","summary":"Simple Virtual MIDI Piano","currentReleaseVersion":"1.0.0","currentReleaseDate":"2022-01-01","iconDesktopUrl":"http://localhost:7777/repo/appstream/x86_64/icons/128x128/net.sourceforge.drumstick-vpiano","iconMobileUrl":"http://localhost:7777/repo/appstream/x86_64/icons/128x128/net.sourceforge.drumstick-vpiano","inStoreSinceDate":null},{"flatpakAppId":"com.giadamusic.Giada","name":"Giada","summary":"Your hardcore loop machine","currentReleaseVersion":"1.0.0","currentReleaseDate":"2022-01-01","iconDesktopUrl":"http://localhost:7777/repo/appstream/x86_64/icons/128x128/com.giadamusic.Giada","iconMobileUrl":"http://localhost:7777/repo/appstream/x86_64/icons/128x128/com.giadamusic.Giada","inStoreSinceDate":null},{"flatpakAppId":"org.nongnu.gsequencer.gsequencer","name":"GSequencer","summary":"Advanced Gtk+ Sequencer","currentReleaseVersion":"1.0.0","currentReleaseDate":"2022-01-01","iconDesktopUrl":"http://localhost:7777/repo/appstream/x86_64/icons/128x128/org.nongnu.gsequencer.gsequencer","iconMobileUrl":"http://localhost:7777/repo/appstream/x86_64/icons/128x128/org.nongnu.gsequencer.gsequencer","inStoreSinceDate":null},{"flatpakAppId":"org.guitarix.guitarix","name":"guitarix","summary":"virtual versatile amplification for Jack/Linux","currentReleaseVersion":"1.0.0","currentReleaseDate":"2022-01-01","iconDesktopUrl":"http://localhost:7777/repo/appstream/x86_64/icons/128x128/org.guitarix.guitarix","iconMobileUrl":"http://localhost:7777/repo/appstream/x86_64/icons/128x128/org.guitarix.guitarix","inStoreSinceDate":null},{"flatpakAppId":"org.guitarix.Guitarix","name":"guitarix","summary":"virtual versatile amplification for Jack/Linux","currentReleaseVersion":"1.0.0","currentReleaseDate":"2022-01-01","iconDesktopUrl":"http://localhost:7777/repo/appstream/x86_64/icons/128x128/org.guitarix.Guitarix","iconMobileUrl":"http://localhost:7777/repo/appstream/x86_64/icons/128x128/org.guitarix.Guitarix","inStoreSinceDate":null},{"flatpakAppId":"org.pipewire.Helvum","name":"Helvum","summary":"Patchbay for PipeWire","currentReleaseVersion":"1.0.0","currentReleaseDate":"2022-01-01","iconDesktopUrl":"http://localhost:7777/repo/appstream/x86_64/icons/128x128/org.pipewire.Helvum","iconMobileUrl":"http://localhost:7777/repo/appstream/x86_64/icons/128x128/org.pipewire.Helvum","inStoreSinceDate":null},{"flatpakAppId":"org.hydrogenmusic.Hydrogen","name":"Hydrogen","summary":"The advanced drum machine","currentReleaseVersion":"1.0.0","currentReleaseDate":"2022-01-01","iconDesktopUrl":"http://localhost:7777/repo/appstream/x86_64/icons/128x128/org.hydrogenmusic.Hydrogen","iconMobileUrl":"http://localhost:7777/repo/appstream/x86_64/icons/128x128/org.hydrogenmusic.Hydrogen","inStoreSinceDate":null},{"flatpakAppId":"jack-keyboard.desktop","name":"JACK Keyboard","summary":"Virtual keyboard for JACK MIDI","currentReleaseVersion":"1.0.0","currentReleaseDate":"2022-01-01","iconDesktopUrl":"http://localhost:7777/repo/appstream/x86_64/icons/128x128/jack-keyboard.desktop","iconMobileUrl":"http://localhost:7777/repo/appstream/x86_64/icons/128x128/jack-keyboard.desktop","inStoreSinceDate":null},{"flatpakAppId":"lmms.desktop","name":"LMMS","summary":"Music sequencer and synthesizer","currentReleaseVersion":"1.0.0","currentReleaseDate":"2022-01-01","iconDesktopUrl":"http://localhost:7777/repo/appstream/x86_64/icons/128x128/lmms.desktop","iconMobileUrl":"http://localhost:7777/repo/appstream/x86_64/icons/128x128/lmms.desktop","inStoreSinceDate":null},{"flatpakAppId":"mcpdisp.desktop","name":"mcpdisp","summary":"Mackie Control Surface Emulator","currentReleaseVersion":"1.0.0","currentReleaseDate":"2022-01-01","iconDesktopUrl":"http://localhost:7777/repo/appstream/x86_64/icons/128x128/mcpdisp.desktop","iconMobileUrl":"http://localhost:7777/repo/appstream/x86_64/icons/128x128/mcpdisp.desktop","inStoreSinceDate":null},{"flatpakAppId":"mcpdisp-ext.desktop","name":"mcpdisp-ext","summary":"Mackie Control Surface Emulator extender","currentReleaseVersion":"1.0.0","currentReleaseDate":"2022-01-01","iconDesktopUrl":"http://localhost:7777/repo/appstream/x86_64/icons/128x128/mcpdisp-ext.desktop","iconMobileUrl":"http://localhost:7777/repo/appstream/x86_64/icons/128x128/mcpdisp-ext.desktop","inStoreSinceDate":null},{"flatpakAppId":"org.mixxx.Mixxx","name":"Mixxx","summary":"Perform live DJ mixes","currentReleaseVersion":"1.0.0","currentReleaseDate":"2022-01-01","iconDesktopUrl":"http://localhost:7777/repo/appstream/x86_64/icons/128x128/org.mixxx.Mixxx","iconMobileUrl":"http://localhost:7777/repo/appstream/x86_64/icons/128x128/org.mixxx.Mixxx","inStoreSinceDate":null},{"flatpakAppId":"org.mixxx.Mixxx","name":"Mixxx DJ Software","summary":"Everything you need to perform live DJ mixes","currentReleaseVersion":"1.0.0","currentReleaseDate":"2022-01-01","iconDesktopUrl":"http://localhost:7777/repo/appstream/x86_64/icons/128x128/org.mixxx.Mixxx","iconMobileUrl":"http://localhost:7777/repo/appstream/x86_64/icons/128x128/org.mixxx.Mixxx","inStoreSinceDate":null},{"flatpakAppId":"io.github.muse_sequencer.Muse","name":"MusE","summary":"Digital Audio Workstation","currentReleaseVersion":"1.0.0","currentReleaseDate":"2022-01-01","iconDesktopUrl":"http://localhost:7777/repo/appstream/x86_64/icons/128x128/io.github.muse_sequencer.Muse","iconMobileUrl":"http://localhost:7777/repo/appstream/x86_64/icons/128x128/io.github.muse_sequencer.Muse","inStoreSinceDate":null},{"flatpakAppId":"org.musescore.MuseScore","name":"MuseScore","summary":"Create, playback, and print sheet music for free","currentReleaseVersion":"1.0.0","currentReleaseDate":"2022-01-01","iconDesktopUrl":"http://localhost:7777/repo/appstream/x86_64/icons/128x128/org.musescore.MuseScore","iconMobileUrl":"http://localhost:7777/repo/appstream/x86_64/icons/128x128/org.musescore.MuseScore","inStoreSinceDate":null},{"flatpakAppId":"org.musescore.MuseScore","name":"MuseScore","summary":"Create, play and print beautiful sheet music","currentReleaseVersion":"1.0.0","currentReleaseDate":"2022-01-01","iconDesktopUrl":"http://localhost:7777/repo/appstream/x86_64/icons/128x128/org.musescore.MuseScore","iconMobileUrl":"http://localhost:7777/repo/appstream/x86_64/icons/128x128/org.musescore.MuseScore","inStoreSinceDate":null},{"flatpakAppId":"org.musescore.MuseScore3","name":"MuseScore","summary":"Create, playback, and print sheet music for free","currentReleaseVersion":"1.0.0","currentReleaseDate":"2022-01-01","iconDesktopUrl":"http://localhost:7777/repo/appstream/x86_64/icons/128x128/org.musescore.MuseScore3","iconMobileUrl":"http://localhost:7777/repo/appstream/x86_64/icons/128x128/org.musescore.MuseScore3","inStoreSinceDate":null},{"flatpakAppId":"org.rncbc.padthv1","name":"padthv1","summary":"an old-school polyphonic additive synthesizer","currentReleaseVersion":"1.0.0","currentReleaseDate":"2022-01-01","iconDesktopUrl":"http://localhost:7777/repo/appstream/x86_64/icons/128x128/org.rncbc.padthv1","iconMobileUrl":"http://localhost:7777/repo/appstream/x86_64/icons/128x128/org.rncbc.padthv1","inStoreSinceDate":null},{"flatpakAppId":"com.polyphone_soundfonts.polyphone","name":"Polyphone","summary":"Create your own instruments to play your favorite music","currentReleaseVersion":"1.0.0","currentReleaseDate":"2022-01-01","iconDesktopUrl":"http://localhost:7777/repo/appstream/x86_64/icons/128x128/com.polyphone_soundfonts.polyphone","iconMobileUrl":"http://localhost:7777/repo/appstream/x86_64/icons/128x128/com.polyphone_soundfonts.polyphone","inStoreSinceDate":null},{"flatpakAppId":"com.polyphone_soundfonts.polyphone","name":"Polyphone","summary":"Turn any sound into a musical instrument.","currentReleaseVersion":"1.0.0","currentReleaseDate":"2022-01-01","iconDesktopUrl":"http://localhost:7777/repo/appstream/x86_64/icons/128x128/com.polyphone_soundfonts.polyphone","iconMobileUrl":"http://localhost:7777/repo/appstream/x86_64/icons/128x128/com.polyphone_soundfonts.polyphone","inStoreSinceDate":null},{"flatpakAppId":"org.rncbc.qjackctl","name":"QjackCtl","summary":"JACK Audio Connection Kit Qt GUI Interface","currentReleaseVersion":"1.0.0","currentReleaseDate":"2022-01-01","iconDesktopUrl":"http://localhost:7777/repo/appstream/x86_64/icons/128x128/org.rncbc.qjackctl","iconMobileUrl":"http://localhost:7777/repo/appstream/x86_64/icons/128x128/org.rncbc.qjackctl","inStoreSinceDate":null},{"flatpakAppId":"qmidiarp.desktop","name":"QMidiArp","summary":"A MIDI Arpeggiator, Step Sequencer and LFO","currentReleaseVersion":"1.0.0","currentReleaseDate":"2022-01-01","iconDesktopUrl":"http://localhost:7777/repo/appstream/x86_64/icons/128x128/qmidiarp.desktop","iconMobileUrl":"http://localhost:7777/repo/appstream/x86_64/icons/128x128/qmidiarp.desktop","inStoreSinceDate":null},{"flatpakAppId":"org.rncbc.qpwgraph","name":"qpwgraph","summary":"A PipeWire Graph Qt GUI Interface","currentReleaseVersion":"1.0.0","currentReleaseDate":"2022-01-01","iconDesktopUrl":"http://localhost:7777/repo/appstream/x86_64/icons/128x128/org.rncbc.qpwgraph","iconMobileUrl":"http://localhost:7777/repo/appstream/x86_64/icons/128x128/org.rncbc.qpwgraph","inStoreSinceDate":null},{"flatpakAppId":"org.rncbc.qsampler","name":"Qsampler","summary":"A LinuxSampler Qt GUI interface","currentReleaseVersion":"1.0.0","currentReleaseDate":"2022-01-01","iconDesktopUrl":"http://localhost:7777/repo/appstream/x86_64/icons/128x128/org.rncbc.qsampler","iconMobileUrl":"http://localhost:7777/repo/appstream/x86_64/icons/128x128/org.rncbc.qsampler","inStoreSinceDate":null},{"flatpakAppId":"org.rncbc.qsynth","name":"Qsynth","summary":"A fluidsynth Qt GUI Interface","currentReleaseVersion":"1.0.0","currentReleaseDate":"2022-01-01","iconDesktopUrl":"http://localhost:7777/repo/appstream/x86_64/icons/128x128/org.rncbc.qsynth","iconMobileUrl":"http://localhost:7777/repo/appstream/x86_64/icons/128x128/org.rncbc.qsynth","inStoreSinceDate":null},{"flatpakAppId":"com.rosegardenmusic.rosegarden.desktop","name":"Rosegarden","summary":"MIDI and Audio Sequencer and Notation Editor","currentReleaseVersion":"1.0.0","currentReleaseDate":"2022-01-01","iconDesktopUrl":"http://localhost:7777/repo/appstream/x86_64/icons/128x128/com.rosegardenmusic.rosegarden.desktop","iconMobileUrl":"http://localhost:7777/repo/appstream/x86_64/icons/128x128/com.rosegardenmusic.rosegarden.desktop","inStoreSinceDate":null},{"flatpakAppId":"org.rncbc.samplv1","name":"samplv1","summary":"an old-school polyphonic sampler","currentReleaseVersion":"1.0.0","currentReleaseDate":"2022-01-01","iconDesktopUrl":"http://localhost:7777/repo/appstream/x86_64/icons/128x128/org.rncbc.samplv1","iconMobileUrl":"http://localhost:7777/repo/appstream/x86_64/icons/128x128/org.rncbc.samplv1","inStoreSinceDate":null},{"flatpakAppId":"schism.desktop","name":"Schism Tracker","summary":"Impulse Tracker clone","currentReleaseVersion":"1.0.0","currentReleaseDate":"2022-01-01","iconDesktopUrl":"http://localhost:7777/repo/appstream/x86_64/icons/128x128/schism.desktop","iconMobileUrl":"http://localhost:7777/repo/appstream/x86_64/icons/128x128/schism.desktop","inStoreSinceDate":null},{"flatpakAppId":"swami.desktop","name":"Swami Instrument Editor","summary":"Create, play and organize MIDI instruments and sounds","currentReleaseVersion":"1.0.0","currentReleaseDate":"2022-01-01","iconDesktopUrl":"http://localhost:7777/repo/appstream/x86_64/icons/128x128/swami.desktop","iconMobileUrl":"http://localhost:7777/repo/appstream/x86_64/icons/128x128/swami.desktop","inStoreSinceDate":null},{"flatpakAppId":"org.rncbc.synthv1","name":"synthv1","summary":"an old-school polyphonic synthesizer","currentReleaseVersion":"1.0.0","currentReleaseDate":"2022-01-01","iconDesktopUrl":"http://localhost:7777/repo/appstream/x86_64/icons/128x128/org.rncbc.synthv1","iconMobileUrl":"http://localhost:7777/repo/appstream/x86_64/icons/128x128/org.rncbc.synthv1","inStoreSinceDate":null},{"flatpakAppId":"tutka.desktop","name":"Tutka MIDI Tracker","summary":"Compose music using MIDI","currentReleaseVersion":"1.0.0","currentReleaseDate":"2022-01-01","iconDesktopUrl":"http://localhost:7777/repo/appstream/x86_64/icons/128x128/tutka.desktop","iconMobileUrl":"http://localhost:7777/repo/appstream/x86_64/icons/128x128/tutka.desktop","inStoreSinceDate":null},{"flatpakAppId":"net.sourceforge.VMPK","name":"VMPK","summary":"Virtual MIDI Piano Keyboard: a MIDI events generator and receiver","currentReleaseVersion":"1.0.0","currentReleaseDate":"2022-01-01","iconDesktopUrl":"http://localhost:7777/repo/appstream/x86_64/icons/128x128/net.sourceforge.VMPK","iconMobileUrl":"http://localhost:7777/repo/appstream/x86_64/icons/128x128/net.sourceforge.VMPK","inStoreSinceDate":null},{"flatpakAppId":"net.sourceforge.projects.yoshimi_2247","name":"Yoshimi","summary":"A Software Synthesizer for Linux","currentReleaseVersion":"1.0.0","currentReleaseDate":"2022-01-01","iconDesktopUrl":"http://localhost:7777/repo/appstream/x86_64/icons/128x128/net.sourceforge.projects.yoshimi_2247","iconMobileUrl":"http://localhost:7777/repo/appstream/x86_64/icons/128x128/net.sourceforge.projects.yoshimi_2247","inStoreSinceDate":null}]