[{"flatpakAppId":"birdfont.desktop","name":"Birdfont","summary":"Font editor","currentReleaseVersion":"1.0.0","currentReleaseDate":"2022-01-01","iconDesktopUrl":"http://localhost:7777/repo/appstream/x86_64/icons/128x128/birdfont.desktop","iconMobileUrl":"http://localhost:7777/repo/appstream/x86_64/icons/128x128/birdfont.desktop","inStoreSinceDate":null},{"flatpakAppId":"org.gnome.Evince","name":"Document Viewer","summary":"Document viewer for popular document formats","currentReleaseVersion":"1.0.0","currentReleaseDate":"2022-01-01","iconDesktopUrl":"http://localhost:7777/repo/appstream/x86_64/icons/128x128/org.gnome.Evince","iconMobileUrl":"http://localhost:7777/repo/appstream/x86_64/icons/128x128/org.gnome.Evince","inStoreSinceDate":null},{"flatpakAppId":"fontmatrix.desktop","name":"Fontmatrix","summary":"A font manager","currentReleaseVersion":"1.0.0","currentReleaseDate":"2022-01-01","iconDesktopUrl":"http://localhost:7777/repo/appstream/x86_64/icons/128x128/fontmatrix.desktop","iconMobileUrl":"http://localhost:7777/repo/appstream/x86_64/icons/128x128/fontmatrix.desktop","inStoreSinceDate":null},{"flatpakAppId":"graide.desktop","name":"Graide","summary":"GRAphite Integrated Development Environment","currentReleaseVersion":"1.0.0","currentReleaseDate":"2022-01-01","iconDesktopUrl":"http://localhost:7777/repo/appstream/x86_64/icons/128x128/graide.desktop","iconMobileUrl":"http://localhost:7777/repo/appstream/x86_64/icons/128x128/graide.desktop","inStoreSinceDate":null},{"flatpakAppId":"org.kde.karbon.desktop","name":"Karbon","summary":"Scalable Graphics","currentReleaseVersion":"1.0.0","currentReleaseDate":"2022-01-01","iconDesktopUrl":"http://localhost:7777/repo/appstream/x86_64/icons/128x128/org.kde.karbon.desktop","iconMobileUrl":"http://localhost:7777/repo/appstream/x86_64/icons/128x128/org.kde.karbon.desktop","inStoreSinceDate":null},{"flatpakAppId":"libreoffice-draw.desktop","name":"LibreOffice Draw","summary":"Graphics editor part of the LibreOffice productivity suite","currentReleaseVersion":"1.0.0","currentReleaseDate":"2022-01-01","iconDesktopUrl":"http://localhost:7777/repo/appstream/x86_64/icons/128x128/libreoffice-draw.desktop","iconMobileUrl":"http://localhost:7777/repo/appstream/x86_64/icons/128x128/libreoffice-draw.desktop","inStoreSinceDate":null},{"flatpakAppId":"org.pencil2d.Pencil2D","name":"Pencil2D","summary":"2D animation software supporting bitmap and vector graphics","currentReleaseVersion":"1.0.0","currentReleaseDate":"2022-01-01","iconDesktopUrl":"http://localhost:7777/repo/appstream/x86_64/icons/128x128/org.pencil2d.Pencil2D","iconMobileUrl":"http://localhost:7777/repo/appstream/x86_64/icons/128x128/org.pencil2d.Pencil2D","inStoreSinceDate":null},{"flatpakAppId":"org.pencil2d.Pencil2D","name":"Pencil2D","summary":"Create 2D animations with ease","currentReleaseVersion":"1.0.0","currentReleaseDate":"2022-01-01","iconDesktopUrl":"http://localhost:7777/repo/appstream/x86_64/icons/128x128/org.pencil2d.Pencil2D","iconMobileUrl":"http://localhost:7777/repo/appstream/x86_64/icons/128x128/org.pencil2d.Pencil2D","inStoreSinceDate":null},{"flatpakAppId":"qelectrotech.desktop","name":"QElectroTech","summary":"Edit electrical diagrams.","currentReleaseVersion":"1.0.0","currentReleaseDate":"2022-01-01","iconDesktopUrl":"http://localhost:7777/repo/appstream/x86_64/icons/128x128/qelectrotech.desktop","iconMobileUrl":"http://localhost:7777/repo/appstream/x86_64/icons/128x128/qelectrotech.desktop","inStoreSinceDate":null},{"flatpakAppId":"org.synfig.SynfigStudio","name":"Synfig Studio","summary":"Create and edit 2D animations and compositions","currentReleaseVersion":"1.0.0","currentReleaseDate":"2022-01-01","iconDesktopUrl":"http://localhost:7777/repo/appstream/x86_64/icons/128x128/org.synfig.SynfigStudio","iconMobileUrl":"http://localhost:7777/repo/appstream/x86_64/icons/128x128/org.synfig.SynfigStudio","inStoreSinceDate":null},{"flatpakAppId":"valentina.desktop","name":"Valentina","summary":"Creating pattern of clothes","currentReleaseVersion":"1.0.0","currentReleaseDate":"2022-01-01","iconDesktopUrl":"http://localhost:7777/repo/appstream/x86_64/icons/128x128/valentina.desktop","iconMobileUrl":"http://localhost:7777/repo/appstream/x86_64/icons/128x128/valentina.desktop","inStoreSinceDate":null}]