{"flatpakAppId":"compton-conf.desktop","name":"Window Effects","summary":"Configure Compton window effects","description":"\n    <p>Qt configuration tool for X composite manager</p>\n    <p>This package contain Compton Configurator.</p>\n  ","developerName":null,"projectLicense":null,"homepageUrl":null,"donationUrl":null,"translateUrl":null,"bugtrackerUrl":null,"helpUrl":null,"categories":[{"name":"Settings"},{"name":"DesktopSettings"}],"downloadFlatpakRefUrl":"compton-conf","currentReleaseVersion":null,"currentReleaseDescription":null,"iconDesktopUrl":"https://appstream.ubuntu.com/media/jammy/c/co/compton-conf.desktop/1765DD4A853364D574157A51D017BB59/icons/128x128/compton-conf_compton.png","iconMobileUrl":"https://appstream.ubuntu.com/media/jammy/c/co/compton-conf.desktop/1765DD4A853364D574157A51D017BB59/icons/128x128/compton-conf_compton.png","screenshots":[],"currentReleaseDate":null,"inStoreSinceDate":null}