{"flatpakAppId":"gmanedit.desktop","name":"gmanedit","summary":"GNOME Manpages Editor","description":"\n    <p>Gtk+ Manpages Editor is an editor for man pages that runs on X with GTK+.</p>\n    <p>Gmanedit is an application which allows you to edit manual pages (man) on Linux/Unix systems.</p>\n    <p>It is like most common HTML editors but more easy. You need to know manpages format.</p>\n  ","developerName":null,"projectLicense":null,"homepageUrl":null,"donationUrl":null,"translateUrl":null,"bugtrackerUrl":null,"helpUrl":null,"categories":[{"name":"Development"}],"downloadFlatpakRefUrl":"gmanedit","currentReleaseVersion":null,"currentReleaseDescription":null,"iconDesktopUrl":"http://localhost:7777/repo/appstream/x86_64/icons/128x128/gmanedit_gmanedit_icon.png","iconMobileUrl":"http://localhost:7777/repo/appstream/x86_64/icons/128x128/gmanedit_gmanedit_icon.png","screenshots":[],"currentReleaseDate":null,"inStoreSinceDate":null}